fpcross/__init__.py
fpcross/equation.py
fpcross/fpcross.py
fpcross/plot.py
fpcross/equation_demo/__init__.py
fpcross/equation_demo/equation_dif.py
fpcross/equation_demo/equation_dum.py
fpcross/equation_demo/equation_oup.py
fpcross-0.5.5.dist-info/LICENSE.txt
fpcross-0.5.5.dist-info/METADATA
fpcross-0.5.5.dist-info/WHEEL
fpcross-0.5.5.dist-info/top_level.txt
fpcross-0.5.5.dist-info/RECORD
