Metadata-Version: 2.1
Name: fpcross
Version: 0.5.5
Summary: Solver in the low-rank tensor-train format with cross approximation approach for solution of the multidimensional Fokker-Planck equation
Home-page: https://github.com/AndreiChertkov/fpcross
Author: Andrei Chertkov
Author-email: andre.chertkov@gmail.com
License: MIT
Project-URL: Source, https://github.com/AndreiChertkov/fpcross
Keywords: Fokker-Planck equation low-rank representation tensor train format TT-decomposition cross approximation probability density estimation
Classifier: Development Status :: 4 - Beta
Classifier: License :: OSI Approved :: MIT License
Classifier: Topic :: Scientific/Engineering
Classifier: Topic :: Scientific/Engineering :: Mathematics
Classifier: Topic :: Scientific/Engineering :: Information Analysis
Classifier: Topic :: Scientific/Engineering :: Artificial Intelligence
Classifier: Intended Audience :: Science/Research
Classifier: Operating System :: OS Independent
Classifier: Programming Language :: Python :: 3
Classifier: Programming Language :: Python :: 3 :: Only
Classifier: Programming Language :: Python :: 3.8
Classifier: Programming Language :: Python :: 3.9
Classifier: Framework :: Jupyter
Requires-Python: >=3.8
License-File: LICENSE.txt
Requires-Dist: teneva >=0.14.7
Requires-Dist: tqdm >=4.64.0
Requires-Dist: matplotlib <3.7.1,>=3.7.0 ; python_version == "3.8"
Requires-Dist: numpy <1.25,>=1.22 ; python_version == "3.8"
Requires-Dist: matplotlib >=3.7.0 ; python_version >= "3.9"
Requires-Dist: numpy >=1.22 ; python_version >= "3.9"
